{
  "trading_pairs": [
    {
      "symbol": "BTCUSDT",
      "enabled": true,
      "timeframes": ["15m", "1h", "4h", "1d"],
      "primary_timeframe": "1h",
      "entry_threshold": 0.65,
      "risk_percentage": 1.0,
      "leverage": 3,
      "take_profit_pct": 2.5,
      "stop_loss_pct": 1.5,
      "trailing_stop_enabled": true,
      "trailing_stop_activation_pct": 1.0,
      "trailing_stop_callback_pct": 0.5,
      "strategies": ["composite", "ml"]
    },
    {
      "symbol": "ETHUSDT",
      "enabled": true,
      "timeframes": ["15m", "1h", "4h", "1d"],
      "primary_timeframe": "1h",
      "entry_threshold": 0.70,
      "risk_percentage": 1.0,
      "leverage": 3,
      "take_profit_pct": 3.0,
      "stop_loss_pct": 2.0,
      "trailing_stop_enabled": true,
      "trailing_stop_activation_pct": 1.2,
      "trailing_stop_callback_pct": 0.6,
      "strategies": ["composite", "ml"]
    },
    {
      "symbol": "BNBUSDT",
      "enabled": true,
      "timeframes": ["15m", "1h", "4h", "1d"],
      "primary_timeframe": "1h",
      "entry_threshold": 0.65,
      "risk_percentage": 1.0,
      "leverage": 2,
      "take_profit_pct": 2.5,
      "stop_loss_pct": 1.5,
      "trailing_stop_enabled": true,
      "trailing_stop_activation_pct": 1.0,
      "trailing_stop_callback_pct": 0.5,
      "strategies": ["composite", "ml"]
    },
    {
      "symbol": "SOLUSDT",
      "enabled": true,
      "timeframes": ["15m", "1h", "4h", "1d"],
      "primary_timeframe": "1h",
      "entry_threshold": 0.70,
      "risk_percentage": 1.0,
      "leverage": 2,
      "take_profit_pct": 3.5,
      "stop_loss_pct": 2.5,
      "trailing_stop_enabled": true,
      "trailing_stop_activation_pct": 1.5,
      "trailing_stop_callback_pct": 0.8,
      "strategies": ["composite", "ml"]
    },
    {
      "symbol": "XRPUSDT",
      "enabled": true,
      "timeframes": ["15m", "1h", "4h", "1d"],
      "primary_timeframe": "1h",
      "entry_threshold": 0.68,
      "risk_percentage": 1.0,
      "leverage": 2,
      "take_profit_pct": 3.0,
      "stop_loss_pct": 2.0,
      "trailing_stop_enabled": true,
      "trailing_stop_activation_pct": 1.2,
      "trailing_stop_callback_pct": 0.6,
      "strategies": ["composite", "ml"]
    },
    {
      "symbol": "AVAXUSDT",
      "enabled": true,
      "timeframes": ["15m", "1h", "4h", "1d"],
      "primary_timeframe": "1h",
      "entry_threshold": 0.72,
      "risk_percentage": 1.0,
      "leverage": 2,
      "take_profit_pct": 4.0,
      "stop_loss_pct": 2.8,
      "trailing_stop_enabled": true,
      "trailing_stop_activation_pct": 1.5,
      "trailing_stop_callback_pct": 0.8,
      "strategies": ["composite", "ml"]
    },
    {
      "symbol": "DOGEUSDT",
      "enabled": true,
      "timeframes": ["15m", "1h", "4h", "1d"],
      "primary_timeframe": "1h",
      "entry_threshold": 0.75,
      "risk_percentage": 0.8,
      "leverage": 2,
      "take_profit_pct": 4.5,
      "stop_loss_pct": 3.0,
      "trailing_stop_enabled": true,
      "trailing_stop_activation_pct": 1.8,
      "trailing_stop_callback_pct": 1.0,
      "strategies": ["composite", "ml"]
    },
    {
      "symbol": "ADAUSDT",
      "enabled": true,
      "timeframes": ["15m", "1h", "4h", "1d"],
      "primary_timeframe": "1h",
      "entry_threshold": 0.68,
      "risk_percentage": 0.9,
      "leverage": 2,
      "take_profit_pct": 3.2,
      "stop_loss_pct": 2.2,
      "trailing_stop_enabled": true,
      "trailing_stop_activation_pct": 1.3,
      "trailing_stop_callback_pct": 0.7,
      "strategies": ["composite", "ml"]
    },
    {
      "symbol": "DOTUSDT",
      "enabled": true,
      "timeframes": ["15m", "1h", "4h", "1d"],
      "primary_timeframe": "1h",
      "entry_threshold": 0.70,
      "risk_percentage": 0.9,
      "leverage": 2,
      "take_profit_pct": 3.5,
      "stop_loss_pct": 2.3,
      "trailing_stop_enabled": true,
      "trailing_stop_activation_pct": 1.4,
      "trailing_stop_callback_pct": 0.7,
      "strategies": ["composite", "ml"]
    }
  ],
  "general_settings": {
    "initial_balance": 10000.0,
    "max_positions": 5,
    "data_lookback_days": 120,
    "check_interval_seconds": 60,
    "ml_features_enabled": true,
    "dynamic_risk_management": true,
    "market_regime_adaptation": true,
    "telegram_notifications": true,
    "notification_level": "all",
    "save_trading_data": true,
    "data_directory": "data",
    "log_level": "INFO"
  },
  "composite_indicator_settings": {
    "indicators": [
      "rsi",
      "macd",
      "ema_cross",
      "bbands",
      "volume_trend",
      "adx",
      "stochastic",
      "obv",
      "atr"
    ],
    "dynamic_weights": true,
    "lookback_period": 20
  },
  "ml_settings": {
    "enabled": true,
    "model_type": "ensemble",
    "base_models": [
      "random_forest",
      "gradient_boosting",
      "neural_network",
      "xgboost",
      "svm"
    ],
    "feature_selection": true,
    "use_model_per_regime": true,
    "retraining_interval_days": 3,
    "prediction_threshold": 0.6,
    "min_prediction_confidence": 0.65,
    "training_data_days": 180,
    "validation_split": 0.2,
    "advanced_features": true,
    "use_volume_profile": true,
    "use_sentiment_analysis": true,
    "use_trend_strength": true,
    "use_correlation_analysis": true,
    "feature_engineering": {
      "fractal_analysis": true,
      "market_structure": true,
      "volatility_analysis": true,
      "momentum_indicators": true,
      "price_patterns": true
    }
  },
  "risk_management_settings": {
    "market_regime_risk_multipliers": {
      "trending_up": 1.2,
      "trending_down": 0.8,
      "ranging": 1.0,
      "volatile": 0.6,
      "breakout": 1.0,
      "neutral": 0.8
    },
    "max_risk_per_trade_pct": 2.0,
    "max_open_trades": 3,
    "correlation_based_sizing": true,
    "auto_adjust_tp_sl": true
  }
}