{
    "risk_level": 15,
    "risk_per_trade_percent": 1.5,
    "max_positions": 7,
    "max_daily_trades": 15,
    "stop_loss_percent": 3.0,
    "take_profit_percent": 4.5,
    "trailing_stop_activation": 2.0,
    "trailing_stop_callback": 0.75,
    "max_drawdown_percent": 7.5,
    "max_daily_loss_percent": 4.5,
    "leverage": 7,
    "entry_confidence_threshold": 70,
    "symbols": ["BTCUSDT", "ETHUSDT", "BNBUSDT", "ADAUSDT", "SOLUSDT", "DOGEUSDT", "XRPUSDT"],
    "timeframes": ["15m", "1h", "4h"],
    "strategy_settings": {
        "rsi_periods": 14,
        "rsi_overbought": 75,
        "rsi_oversold": 25,
        "macd_fast": 12,
        "macd_slow": 26,
        "macd_signal": 9,
        "ma_fast": 20,
        "ma_slow": 50,
        "ma_trend": 200,
        "bollinger_periods": 20,
        "bollinger_std_dev": 2.2,
        "volume_threshold": 1.75
    }
}