{
    "max_open_positions": 4,
    "position_size_percent": 3.0,
    "stop_loss_percent": 2.0,
    "take_profit_percent": 4.0,
    "trailing_stop_percent": 0.7,
    "max_daily_trades": 12,
    "max_daily_drawdown_percent": 7.0,
    "use_adaptive_position_sizing": true,
    "use_dynamic_stop_loss": true,
    "leverage": 3,
    "risk_multipliers": {
        "stop_loss_multiplier": 2.0,
        "take_profit_multiplier": 2.0,
        "trailing_stop_callback": 0.2,
        "position_size_multiplier": 2.0
    }
}